LICENSE.txt
MANIFEST.in
setup.py
tests.py
cronpy/__init__.py
cronpy/cronpy.py
cronpy.egg-info/PKG-INFO
cronpy.egg-info/SOURCES.txt
cronpy.egg-info/dependency_links.txt
cronpy.egg-info/not-zip-safe
cronpy.egg-info/top_level.txt